hussein/__init__.py
hussein/main.py
tests/__init__.py
hussein-1.0.8.dist-info/LICENSE
hussein-1.0.8.dist-info/METADATA
hussein-1.0.8.dist-info/WHEEL
hussein-1.0.8.dist-info/entry_points.txt
hussein-1.0.8.dist-info/top_level.txt
hussein-1.0.8.dist-info/RECORD
